bus_wizard/__init__.py
bus_wizard/bus_driver_scheduling.py
bus_wizard/driver.py
bus_wizard/task.py
bus_wizard/task_chain_finder.py
bus_wizard-0.0.7.dist-info/METADATA
bus_wizard-0.0.7.dist-info/WHEEL
bus_wizard-0.0.7.dist-info/top_level.txt
bus_wizard-0.0.7.dist-info/RECORD
